tensorflow/__init__.py
tensorflow/core/example/example_parser_configuration_pb2.py
tensorflow/core/example/example_parser_configuration_pb2_grpc.py
tensorflow/core/example/example_pb2.py
tensorflow/core/example/example_pb2_grpc.py
tensorflow/core/example/feature_pb2.py
tensorflow/core/example/feature_pb2_grpc.py
tensorflow/core/framework/allocation_description_pb2.py
tensorflow/core/framework/allocation_description_pb2_grpc.py
tensorflow/core/framework/api_def_pb2.py
tensorflow/core/framework/api_def_pb2_grpc.py
tensorflow/core/framework/attr_value_pb2.py
tensorflow/core/framework/attr_value_pb2_grpc.py
tensorflow/core/framework/cost_graph_pb2.py
tensorflow/core/framework/cost_graph_pb2_grpc.py
tensorflow/core/framework/dataset_metadata_pb2.py
tensorflow/core/framework/dataset_metadata_pb2_grpc.py
tensorflow/core/framework/dataset_options_pb2.py
tensorflow/core/framework/dataset_options_pb2_grpc.py
tensorflow/core/framework/device_attributes_pb2.py
tensorflow/core/framework/device_attributes_pb2_grpc.py
tensorflow/core/framework/full_type_pb2.py
tensorflow/core/framework/full_type_pb2_grpc.py
tensorflow/core/framework/function_pb2.py
tensorflow/core/framework/function_pb2_grpc.py
tensorflow/core/framework/graph_pb2.py
tensorflow/core/framework/graph_pb2_grpc.py
tensorflow/core/framework/graph_transfer_info_pb2.py
tensorflow/core/framework/graph_transfer_info_pb2_grpc.py
tensorflow/core/framework/kernel_def_pb2.py
tensorflow/core/framework/kernel_def_pb2_grpc.py
tensorflow/core/framework/log_memory_pb2.py
tensorflow/core/framework/log_memory_pb2_grpc.py
tensorflow/core/framework/model_pb2.py
tensorflow/core/framework/model_pb2_grpc.py
tensorflow/core/framework/node_def_pb2.py
tensorflow/core/framework/node_def_pb2_grpc.py
tensorflow/core/framework/op_def_pb2.py
tensorflow/core/framework/op_def_pb2_grpc.py
tensorflow/core/framework/reader_base_pb2.py
tensorflow/core/framework/reader_base_pb2_grpc.py
tensorflow/core/framework/resource_handle_pb2.py
tensorflow_protobuf-2.11.0.dist-info/LICENSE
tensorflow_protobuf-2.11.0.dist-info/METADATA
tensorflow_protobuf-2.11.0.dist-info/WHEEL
tensorflow_protobuf-2.11.0.dist-info/top_level.txt
tensorflow_protobuf-2.11.0.dist-info/RECORD
