Metadata-Version: 2.1
Name: tensorflow-protobuf
Version: 2.11.0
Summary: Protobuf files from TensorFlow and TensorFlow-Serving
Home-page: https://github.com/alexeygrigorev/tensorflow-protobufr
Author: TensorFlow authors
Author-email: alexey@datatalks.club
License: Original Tensorflow licence
Platform: UNKNOWN
Classifier: Programming Language :: Python :: 3
Classifier: Programming Language :: Python :: 3.7
Classifier: Programming Language :: Python :: 3.8
Classifier: Programming Language :: Python :: 3.9
Requires-Dist: protobuf
